syscryptpackagesV4/__init__.py
syscryptpackagesV4-1.1.0.dist-info/METADATA
syscryptpackagesV4-1.1.0.dist-info/WHEEL
syscryptpackagesV4-1.1.0.dist-info/top_level.txt
syscryptpackagesV4-1.1.0.dist-info/RECORD
