Metadata-Version: 2.1
Name: syscryptpackagesV4
Version: 1.1.0
Summary: agkkebebfdufdkdjbraaigtgzspcztjznynqbts
Home-page: UNKNOWN
Author: anbydrew8q8
Author-email: anbydrew8q8@gmail.com
License: UNKNOWN
Keywords: python
Platform: UNKNOWN
Classifier: Operating System :: Microsoft :: Windows
